all2vec/__init__.py
all2vec-0.6.0.dist-info/DESCRIPTION.rst
all2vec-0.6.0.dist-info/METADATA
all2vec-0.6.0.dist-info/RECORD
all2vec-0.6.0.dist-info/WHEEL
all2vec-0.6.0.dist-info/metadata.json
all2vec-0.6.0.dist-info/top_level.txt
all2vec-0.6.0.dist-info/zip-safe
